shotstack_sdk/__init__.py
shotstack_sdk/api_client.py
shotstack_sdk/configuration.py
shotstack_sdk/exceptions.py
shotstack_sdk/rest.py
shotstack_sdk/api/__init__.py
shotstack_sdk/api/edit_api.py
shotstack_sdk/api/serve_api.py
shotstack_sdk/apis/__init__.py
shotstack_sdk/model/__init__.py
shotstack_sdk/model/asset.py
shotstack_sdk/model/asset_render_response.py
shotstack_sdk/model/asset_response.py
shotstack_sdk/model/asset_response_attributes.py
shotstack_sdk/model/asset_response_data.py
shotstack_sdk/model/audio_asset.py
shotstack_sdk/model/clip.py
shotstack_sdk/model/crop.py
shotstack_sdk/model/destinations.py
shotstack_sdk/model/edit.py
shotstack_sdk/model/flip_transformation.py
shotstack_sdk/model/font.py
shotstack_sdk/model/html_asset.py
shotstack_sdk/model/image_asset.py
shotstack_sdk/model/luma_asset.py
shotstack_sdk/model/merge_field.py
shotstack_sdk/model/mux_destination.py
shotstack_sdk/model/mux_destination_options.py
shotstack_sdk/model/offset.py
shotstack_sdk/model/output.py
shotstack_sdk/model/poster.py
shotstack_sdk/model/probe_response.py
shotstack_sdk/model/queued_response.py
shotstack_sdk/model/queued_response_data.py
shotstack_sdk/model/range.py
shotstack_sdk/model/render_response.py
shotstack_sdk/model/rotate_transformation.py
shotstack_sdk/model/shotstack_destination.py
shotstack_sdk/model/size.py
shotstack_sdk/model/skew_transformation.py
shotstack_sdk/model/soundtrack.py
shotstack_sdk/model/template.py
shotstack_sdk/model/template_data_response.py
shotstack_sdk/model/template_data_response_data.py
shotstack_sdk/model/template_list_response.py
shotstack_sdk/model/template_list_response_data.py
shotstack_sdk/model/template_list_response_item.py
shotstack_sdk/model/template_render.py
shotstack_sdk/model/template_response.py
shotstack_sdk/model/template_response_data.py
shotstack_sdk/model/thumbnail.py
shotstack_sdk/model/timeline.py
shotstack_sdk/model/title_asset.py
shotstack_sdk/model/track.py
shotstack_sdk/model/transformation.py
shotstack_sdk-0.2.0.dist-info/METADATA
shotstack_sdk-0.2.0.dist-info/WHEEL
shotstack_sdk-0.2.0.dist-info/top_level.txt
shotstack_sdk-0.2.0.dist-info/RECORD
