Metadata-Version: 2.1
Name: shotstack-sdk
Version: 0.2.0
Summary: Shotstack
Home-page: https://shotstack.io
Author: Shotstack
Author-email: pypi@shotstack.io
License: UNKNOWN
Keywords: Shotstack
Platform: UNKNOWN
Requires-Python: >=3.6
Requires-Dist: urllib3 (>=1.25.3)
Requires-Dist: python-dateutil
